setup.py
flumelogger/__init__.py
flumelogger/errors.py
flumelogger/eventserver.py
flumelogger/handler.py
flumelogger/utils.py
flumelogger.egg-info/PKG-INFO
flumelogger.egg-info/SOURCES.txt
flumelogger.egg-info/dependency_links.txt
flumelogger.egg-info/requires.txt
flumelogger.egg-info/top_level.txt
flumelogger/flumeng/ThriftSourceProtocol.py
flumelogger/flumeng/__init__.py
flumelogger/flumeng/constants.py
flumelogger/flumeng/ttypes.py
flumelogger/flumeog/ThriftFlumeEventServer.py
flumelogger/flumeog/__init__.py
flumelogger/flumeog/constants.py
flumelogger/flumeog/ttypes.py