Metadata-Version: 1.1
Name: flumelogger
Version: 0.4.3
Summary: Flume logging handler for sending log events to Flume
Home-page: http://github.com/lsjostro/flumelogger
Author: Lars Sjostrom
Author-email: lars@radicore.se
License: UNKNOWN
Platform: UNKNOWN
Classifier: Intended Audience :: Developers
Classifier: License :: OSI Approved :: BSD License
Classifier: Operating System :: OS Independent
Classifier: Programming Language :: Python
Classifier: Topic :: Software Development :: Libraries :: Python Modules
